{
  "ConceptSets": [
    {
      "id": 0,
      "name": "[WHC] VMS",
      "expression": {
        "items": [
          {
            "concept": {
              "CONCEPT_CLASS_ID": "Clinical Finding",
              "CONCEPT_CODE": "70670009",
              "CONCEPT_ID": 4322635,
              "CONCEPT_NAME": "Abnormal vasomotor function",
              "DOMAIN_ID": "Condition",
              "INVALID_REASON": "V",
              "INVALID_REASON_CAPTION": "Valid",
              "STANDARD_CONCEPT": "S",
              "STANDARD_CONCEPT_CAPTION": "Standard",
              "VOCABULARY_ID": "SNOMED"
            }
          },
          {
            "concept": {
              "CONCEPT_CLASS_ID": "Clinical Finding",
              "CONCEPT_CODE": "427368007",
              "CONCEPT_ID": 4144760,
              "CONCEPT_NAME": "Climacteric flushing",
              "DOMAIN_ID": "Condition",
              "INVALID_REASON": "V",
              "INVALID_REASON_CAPTION": "Valid",
              "STANDARD_CONCEPT": "S",
              "STANDARD_CONCEPT_CAPTION": "Standard",
              "VOCABULARY_ID": "SNOMED"
            }
          },
          {
            "concept": {
              "CONCEPT_CLASS_ID": "Clinical Finding",
              "CONCEPT_CODE": "106002000",
              "CONCEPT_ID": 4024558,
              "CONCEPT_NAME": "Disorder associated with menstruation AND/OR menopause",
              "DOMAIN_ID": "Condition",
              "INVALID_REASON": "V",
              "INVALID_REASON_CAPTION": "Valid",
              "STANDARD_CONCEPT": "S",
              "STANDARD_CONCEPT_CAPTION": "Standard",
              "VOCABULARY_ID": "SNOMED"
            }
          },
          {
            "concept": {
              "CONCEPT_CLASS_ID": "Clinical Finding",
              "CONCEPT_CODE": "OMOP5166051",
              "CONCEPT_ID": 1340396,
              "CONCEPT_NAME": "Exacerbation of menopausal symptom",
              "DOMAIN_ID": "Condition",
              "INVALID_REASON": "V",
              "INVALID_REASON_CAPTION": "Valid",
              "STANDARD_CONCEPT": "S",
              "STANDARD_CONCEPT_CAPTION": "Standard",
              "VOCABULARY_ID": "OMOP Extension"
            }
          },
          {
            "concept": {
              "CONCEPT_CLASS_ID": "Clinical Finding",
              "CONCEPT_CODE": "224962007",
              "CONCEPT_ID": 4075830,
              "CONCEPT_NAME": "Hot sweats",
              "DOMAIN_ID": "Condition",
              "INVALID_REASON": "V",
              "INVALID_REASON_CAPTION": "Valid",
              "STANDARD_CONCEPT": "S",
              "STANDARD_CONCEPT_CAPTION": "Standard",
              "VOCABULARY_ID": "SNOMED"
            }
          },
          {
            "concept": {
              "CONCEPT_CLASS_ID": "Clinical Finding",
              "CONCEPT_CODE": "266677000",
              "CONCEPT_ID": 441628,
              "CONCEPT_NAME": "Menopausal and postmenopausal disorders",
              "DOMAIN_ID": "Condition",
              "INVALID_REASON": "V",
              "INVALID_REASON_CAPTION": "Valid",
              "STANDARD_CONCEPT": "S",
              "STANDARD_CONCEPT_CAPTION": "Standard",
              "VOCABULARY_ID": "SNOMED"
            }
          },
          {
            "concept": {
              "CONCEPT_CLASS_ID": "Clinical Finding",
              "CONCEPT_CODE": "198436008",
              "CONCEPT_ID": 4113666,
              "CONCEPT_NAME": "Menopausal flushing",
              "DOMAIN_ID": "Condition",
              "INVALID_REASON": "V",
              "INVALID_REASON_CAPTION": "Valid",
              "STANDARD_CONCEPT": "S",
              "STANDARD_CONCEPT_CAPTION": "Standard",
              "VOCABULARY_ID": "SNOMED"
            }
          },
          {
            "concept": {
              "CONCEPT_CLASS_ID": "Clinical Finding",
              "CONCEPT_CODE": "68811000",
              "CONCEPT_ID": 4286186,
              "CONCEPT_NAME": "Menopausal problem",
              "DOMAIN_ID": "Condition",
              "INVALID_REASON": "V",
              "INVALID_REASON_CAPTION": "Valid",
              "STANDARD_CONCEPT": "S",
              "STANDARD_CONCEPT_CAPTION": "Standard",
              "VOCABULARY_ID": "SNOMED"
            }
          },
          {
            "concept": {
              "CONCEPT_CLASS_ID": "Clinical Finding",
              "CONCEPT_CODE": "21801002",
              "CONCEPT_ID": 4071683,
              "CONCEPT_NAME": "Menopausal symptom",
              "DOMAIN_ID": "Condition",
              "INVALID_REASON": "V",
              "INVALID_REASON_CAPTION": "Valid",
              "STANDARD_CONCEPT": "S",
              "STANDARD_CONCEPT_CAPTION": "Standard",
              "VOCABULARY_ID": "SNOMED"
            }
          },
          {
            "concept": {
              "CONCEPT_CLASS_ID": "Clinical Finding",
              "CONCEPT_CODE": "123756000",
              "CONCEPT_ID": 439082,
              "CONCEPT_NAME": "Menopausal syndrome",
              "DOMAIN_ID": "Condition",
              "INVALID_REASON": "V",
              "INVALID_REASON_CAPTION": "Valid",
              "STANDARD_CONCEPT": "S",
              "STANDARD_CONCEPT_CAPTION": "Standard",
              "VOCABULARY_ID": "SNOMED"
            }
          },
          {
            "concept": {
              "CONCEPT_CLASS_ID": "Clinical Finding",
              "CONCEPT_CODE": "42984000",
              "CONCEPT_ID": 4181178,
              "CONCEPT_NAME": "Night sweats",
              "DOMAIN_ID": "Condition",
              "INVALID_REASON": "V",
              "INVALID_REASON_CAPTION": "Valid",
              "STANDARD_CONCEPT": "S",
              "STANDARD_CONCEPT_CAPTION": "Standard",
              "VOCABULARY_ID": "SNOMED"
            }
          },
          {
            "concept": {
              "CONCEPT_CLASS_ID": "Clinical Finding",
              "CONCEPT_CODE": "403389006",
              "CONCEPT_ID": 4301021,
              "CONCEPT_NAME": "Postmenopausal flushing",
              "DOMAIN_ID": "Condition",
              "INVALID_REASON": "V",
              "INVALID_REASON_CAPTION": "Valid",
              "STANDARD_CONCEPT": "S",
              "STANDARD_CONCEPT_CAPTION": "Standard",
              "VOCABULARY_ID": "SNOMED"
            }
          }
        ]
      }
    }
  ],
  "PrimaryCriteria": {
    "CriteriaList": [
      {
        "ConditionOccurrence": {
          "CodesetId": 0
        }
      }
    ],
    "ObservationWindow": {
      "PriorDays": 0,
      "PostDays": 0
    },
    "PrimaryCriteriaLimit": {
      "Type": "First"
    }
  },
  "QualifiedLimit": {
    "Type": "First"
  },
  "ExpressionLimit": {
    "Type": "First"
  },
  "InclusionRules": [],
  "CensoringCriteria": [],
  "CollapseSettings": {
    "CollapseType": "ERA",
    "EraPad": 0
  },
  "CensorWindow": {},
  "cdmVersionRange": ">=5.0.0"
}